KeywordMasking/__init__.py
KeywordMasking-1.0.dist-info/LICENSE.txt
KeywordMasking-1.0.dist-info/METADATA
KeywordMasking-1.0.dist-info/WHEEL
KeywordMasking-1.0.dist-info/top_level.txt
KeywordMasking-1.0.dist-info/RECORD
