Metadata-Version: 2.1
Name: KeywordMasking
Version: 1.0
Summary: This package performs keyword masking given a list of words/keywords.
Home-page: UNKNOWN
Author: Shahriar Golchin
Author-email: golchin@arizona.edu
License: UNKNOWN
Platform: UNKNOWN
License-File: LICENSE.txt
